Workbook

Sheet Hist_Data
A2: Ather Energy Limited - Audited Baseline Metrics
A4: Financial Metric / Operating Parameter | B4: FY24 Baseline | C4: FY25 Baseline | D4: YoY Growth / Logic
A5: Consolidated Revenue (INR Cr) | B5: 2296 | C5: 3783 | D5: =(C5-B5)/B5 -> 0.64764808
A6: Core Payment Gateway Revenue (INR Cr) | B6: 1882.72 | C6: 3120 | D6: =(C6-B6)/B6 -> 0.65717685
A7: Gross Profit (INR Cr) | B7: 906 | C7: 1277 | D7: =(C7-B7)/B7 -> 0.40949227
A8: Gross Profit Margin (%) | B8: =B7/B5 -> 0.3945993 | C8: =C7/C5 -> 0.33756278 | D8: Core PG Operating Efficiency
A9: Core PG Adjusted EBITDA (INR Cr) | B9: 185 | C9: 340 | D9: Operating Cash Flow Positive
A10: Annualized Total Payment Volume (TPV $` Bn) | B10: 150 | C10: 180 | D10: =(C10-B10)/B10 -> 0.2
A11: India Blended Net Take Rate (%) | B11: 0.0032 | C11: 0.003 | D11: Constrained by Zero-MDR UPI
A12: India Corporate Tax Rate (%) | B12: 0.2517 | C12: 0.2517 | D12: Sec 115BAA Statutory Rate
A13: USD / INR Exchange Rate | B13: 83.2 | C13: 86.5 | D13: Spot Baseline Rate

Sheet GCC_Expansion_Assumptions
A2: Track 04: International Market Entry Assumptions
A3: Active Scenario Selector (1 = Base, 2 = Bull, 3 = Bear): | C3: 1
A5: Expansion Parameter / Driver | B5: UAE Model (Hub) | C5: KSA Model (Spoke) | D5: Modeling Logic / Driver"
A6: Initial Greenfield CAPEX ($ Mn) | B6: =CHOOSE($C$3, 15, 18, 12) -> 15 | C6: 22 | D6: Setup, Licensing, Infrastructure
A7: Year 1 Enterprise Merchants | B7: =CHOOSE($C$3, 12000, 15000, 9000) -> 12000 | C7: 8500 | D7: Target Merchant Pool
A8: Year 1 Initial TPV ($ Bn) | B8: =CHOOSE($C$3, 3.5, 4.2, 2.6) -> 3.5 | C8: 2.8 | D8: Initial Processed Volume
A9: Annual TPV Growth Rate (%) | B9: 0.45 | C9: 0.55 | D9: Regional FinTech CAGR
A10: Gross Merchant Discount Rate (MDR %) | B10: 0.0245 | C10: 0.0265 | D10: Fee Charged to Merchants
A11: Network & Interchange Cost (%) | B11: 0.0155 | C11: 0.0165 | D11: Visa/Mastercard/Mada Rail Fee
A12: Net Take Rate Margin (%) | B12: =B10-B11 -> 0.009 | C12: =C10-C11 -> 0.01 | D12: Net Retained Margin
A13: Host Corporate Tax Rate (%) | B13: 0.09 | C13: 0.2 | D13: Statutory Host Country Tax
A14: OpEx Ratio (% of Revenue) | B14: 0.42 | C14: 0.48 | D14: Operating Overhead Ratio

Sheet Unit_Economics_Pricing
A2: 5-Year Regional Projections & Unit Economics (2027-2031)
A4: Line Item ($ Mn) | B4: =TPV * Gross_MDR | C4: 2027 (Yr 1) | D4: 2028 (Yr 2) | E4: 2029 (Yr 3) | F4: 2030 (Yr 4) | G4: 2031 (Yr 5)
A5: Total GCC TPV ($ Mn) | B5: =Prev_TPV * (1 + Growth) | C5: =GCC_Expansion_Assumptions!$B$8*1000 -> 3500 | D5: =C5*(1+GCC_Expansion_Assumptions!$B$9) -> 5075 | E5: =D5*(1+GCC_Expansion_Assumptions!$B$9) -> 7358.75 | F5: =E5*(1+GCC_Expansion_Assumptions!$B$9) -> 10670.188 | G5: =F5*(1+GCC_Expansion_Assumptions!$B$9) -> 15471.772
A6: Gross Processing Revenue | B6: =TPV * Gross_MDR | C6: =C5*GCC_Expansion_Assumptions!$B$10 -> 85.75 | D6: =D5*GCC_Expansion_Assumptions!$B$10 -> 124.3375 | E6: =E5*GCC_Expansion_Assumptions!$B$10 -> 180.28938 | F6: =F5*GCC_Expansion_Assumptions!$B$10 -> 261.41959 | G6: =G5*GCC_Expansion_Assumptions!$B$10 -> 379.05841
A7: Interchange & Scheme Costs | B7: =TPV * Interchange | C7: =C5*GCC_Expansion_Assumptions!$B$11 -> 54.25 | D7: =D5*GCC_Expansion_Assumptions!$B$11 -> 78.6625 | E7: =E5*GCC_Expansion_Assumptions!$B$11 -> 114.06063 | F7: =F5*GCC_Expansion_Assumptions!$B$11 -> 165.38791 | G7: =G5*GCC_Expansion_Assumptions!$B$11 -> 239.81246
A8: Net Gross Profit ($ Mn) | B8: =Gross_Rev - Interchange | C8: =C6-C7 -> 31.5 | D8: =D6-D7 -> 45.675 | E8: =E6-E7 -> 66.22875 | F8: =F6-F7 -> 96.031688 | G8: =G6-G7 -> 139.24595
A9: Gross Profit Margin (%) | B9: =Net_Gross_Profit / Gross_Rev | C9: =C8/C6 -> 0.36734694 | D9: =D8/D6 -> 0.36734694 | E9: =E8/E6 -> 0.36734694 | F9: =F8/F6 -> 0.36734694 | G9: =G8/G6 -> 0.36734694
A10: Operating Expenses ($ Mn) | B10: =Gross_Rev * OpEx_Ratio | C10: =C6*GCC_Expansion_Assumptions!$B$14 -> 36.015 | D10: =D6*GCC_Expansion_Assumptions!$B$14 -> 52.22175 | E10: =E6*GCC_Expansion_Assumptions!$B$14 -> 75.721537 | F10: =F6*GCC_Expansion_Assumptions!$B$14 -> 109.79623 | G10: =G6*GCC_Expansion_Assumptions!$B$14 -> 159.20453
A11: EBITDA ($ Mn) | B11: =Net_Gross_Profit - OpEx | C11: =C8-C10 -> -4.515 | D11: =D8-D10 -> -6.54675 | E11: =E8-E10 -> -9.4927875 | F11: =F8-F10 -> -13.764542 | G11: =G8-G10 -> -19.958586
A12: Net Operating Cash Flow | B12: =Net_GP - (Gross_Rev * 0.35) | C12: =C8-(C6*0.35) -> 1.4875 | D12: =D8-(D6*0.35) -> 2.156875 | E12: =E8-(E6*0.35) -> 3.1274688 | F12: =F8-(F6*0.35) -> 4.5348297 | G12: =G8-(G6*0.35) -> 6.575503

Sheet Valuation_FX_Tax
A2: Financial Engineering: WACC, DTAA Tax, FX VaR & Valuation
A4: 1. Cost of Capital (WACC Calculation Engine)
A5: Cost of Equity (Ke) | B5: 0.125 | C5: CAPM Risk-Adjusted Equity Benchmark
A6: Pre-Tax Cost of Debt (Kd) | B6: 0.085 | C6: Debt Financing Rate
A7: Weight of Equity (We) | B7: 0.85 | C7: Target Equity Ratio
A8: Weight of Debt (Wd) | B8: 0.15 | C8: Target Debt Ratio
A9: India Tax Rate (T) | B9: =Hist_Data!C12 -> 0.2517 | C9: Statutory Home Country Corporate Tax Rate
A10: GCC Country Risk Premium (CRP) | B10: 0.015 | C10: Sovereign Risk Spread
A11: Calculated WACC (%) | B11: =(B5*B7)+(B6*B8*(1-B9))+B10 -> 0.13079082 | C11: Discount Rate Baseline (11.83%)
A13: 2. Cross-Border Tax Arbitrage & DTAA Schedule (Case 5)
A14: Host Country Tax (UAE) | B14: =GCC_Expansion_Assumptions!B13 -> 0.09 | C14: Statutory UAE Corporate Tax Rate (9.00%)
A15: Home Country Tax (India) | B15: =Hist_Data!C12 -> 0.2517 | C15: Statutory Indian Corporate Tax Rate (25.17%)
A16: Foreign Tax Credit (FTC) Credit | B16: =MIN(B14, B15) -> 0.09 | C16: DTAA Credit Capped at Host Tax Rate Paid
A17: Net Tax Payable in India | B17: =MAX(0, B15-B14) -> 0.1617 | C17: Residual Liability Paid to Indian Tax Authorities
A18: Total Effective Tax Rate (%) | B18: =B14+B17 -> 0.2517 | C18: Total Capped Tax Rate (25.17%)
A21: 3. Foreign Exchange Risk & Value-at-Risk (VaR) Engine (Case 3)
A22: 1-Year Cash Flow Exposure ($ Mn) | B22: 45 | C22: Net Annual Foreign Exchange Inflows
A23: Annual Currency Volatility (s) | B23: 0.052 | C23: AED/INR Historical Volatility
A24: 95% Confidence Z-Score | B24: 1.645 | C24: One-Tailed Gaussian Z-Score
A25: Unhedged 1-Year VaR ($ Mn) | B25: =B22*B23*B24 -> 3.8493 | C25: Maximum Expected Loss at 95% Confidence ($3.85 Mn)
A26: Hedging Coverage Ratio | B26: 0.8 | C26: 50% Forwards + 30% Currency Collar
A27: Hedged 1-Year VaR ($ Mn) | B27: =B25*(1-B26) -> 0.76986 | C27: Residual Post-Hedge Risk ($0.77 Mn)
A28: VaR Risk Reduction (%) | B28: =(B25-B27)/B25 -> 0.8 | C28: Risk Mitigation Yield (80.00%)
A30: 4. Expansion DCF Valuation & Investment Metrics (Case 4)
A31: Initial Greenfield CAPEX ($ Mn) | B31: =-GCC_Expansion_Assumptions!B6 -> -15
A32: 5-Year Net Cash Flow Array | C32: =Unit_Economics_Pricing!C12 -> 1.4875 | D32: =Unit_Economics_Pricing!D12 -> 2.156875 | E32: =Unit_Economics_Pricing!E12 -> 3.1274688 | F32: =Unit_Economics_Pricing!F12 -> 4.5348297 | G32: =Unit_Economics_Pricing!G12 -> 6.575503
A34: Terminal Growth Rate (g) | B34: 0.035
A35: Terminal Value (TV) ($ Mn) | B35: =(G32*(1+B34))/(B11-B34) -> 71.046947
A36: Net Present Value (NPV) ($ Mn) | B36: =NPV(B11, C32:G32) + (B35/((1+B11)^5)) + B31 -> 34.921952
A37: Internal Rate of Return (IRR %) | B37: =IRR(B31:G32) -> 0.049177741
